yfinhanced/__init__.py
yfinhanced/_version.py
yfinhanced/main.py
yfinhanced/yfinhanced_pb2.py
yfinhanced/yfws_client.py
yfinhanced-0.1.11.dist-info/METADATA
yfinhanced-0.1.11.dist-info/WHEEL
yfinhanced-0.1.11.dist-info/top_level.txt
yfinhanced-0.1.11.dist-info/RECORD
