Metadata-Version: 2.1
Name: yfinhanced
Version: 0.1.11
Summary: A python wrapper around the yahoo finance API that leverages pandas DataFrames
Home-page: https://github.com/ME-64/yfinhanced
Author: ME-64
Author-email: milo_elliott@icloud.com
License: MIT
Keywords: api wrapper,yahoo finance,markets
Platform: UNKNOWN
Classifier: Development Status :: 3 - Alpha
Classifier: Intended Audience :: Developers
Classifier: License :: OSI Approved :: MIT License
Classifier: Programming Language :: Python :: 3.7
Classifier: Programming Language :: Python :: 3.8
Classifier: Programming Language :: Python :: 3.9
Requires-Dist: pandas (<2,>1)
Requires-Dist: aiohttp (<4,>3)
Requires-Dist: asyncio (<4,>3)
Requires-Dist: pytz
Requires-Dist: requests (<3,>2)
Provides-Extra: dev
Requires-Dist: pytest (<8,>7) ; extra == 'dev'
Requires-Dist: pyteset-asyncio (<1,>0.17) ; extra == 'dev'
